py3cli-1.0.1.dist-info/METADATA
py3cli-1.0.1.dist-info/RECORD
py3cli-1.0.1.dist-info/WHEEL
py3cli-1.0.1.dist-info/top_level.txt
pycli/__init__.py
pycli/cli.py
pycli/tests/base_test.py
pycli/tests/test_advanced.py
pycli/tests/test_base.py
